Workbook
Name Slicer_Manager: #N/A

Sheet Cover Page
C4: Data Analysis Start File
C9: Get 10% OFF our course using coupon code EMAIL10
C11: Get Our Excel for Business & Finance Course
C15: Made by Kenji Explains / Career Principles
C16: Note
C17: All content is copyright material of Kenji Explains / Career Principles
C18: This Excel model may not be reproduced or distributed by any means, including printing, screencapturing, or any other method without the prior permission of the publisher.

Sheet Breakdown
B2: Order ID | C2: Date | D2: Product | E2: Price | F2: Purchase Type | G2: Payment Method | H2: Manager | I2: Quantity | J2: City | K2: Country/region | L2: Revenue
B3: 10452 | C3: 44872 | D3: Fries | E3: 3.49 | F3: Online | G3: Gift Card | H3: Tom Jackson | I3: 574 | J3: #VALUE! | K3: {=_FV(Table2[[#This Row],[City]],"Country/region",TRUE)} -> #VALUE! | L3: =Table2[[#This Row],[Quantity]]*Table2[[#This Row],[Price]] -> 2003.26 | O3: First step is to convert this into a Table by highlighting the whole data set (select one cell) and using the shortcut ctrl + t | T3: Documentation done by Euan Garcia
B4: 10453 | C4: 44872 | D4: Beverages | E4: 2.95 | F4: Online | G4: Gift Card | H4: Pablo Perez | I4: 746 | J4: #VALUE! | K4: {=_FV(Table2[[#This Row],[City]],"Country/region",TRUE)} -> #VALUE! | L4: =Table2[[#This Row],[Quantity]]*Table2[[#This Row],[Price]] -> 2200.7
B5: 10454 | C5: 44872 | D5: Sides & Other | E5: 4.99 | F5: In-store | G5: Gift Card | H5: Joao Silva | I5: 201 | J5: #VALUE! | K5: {=_FV(Table2[[#This Row],[City]],"Country/region",TRUE)} -> #VALUE! | L5: =Table2[[#This Row],[Quantity]]*Table2[[#This Row],[Price]] -> 1002.99
B6: 10455 | C6: 44873 | D6: Burgers | E6: 12.99 | F6: In-store | G6: Credit Card | H6: Walter Muller | I6: 570 | J6: #VALUE! | K6: {=_FV(Table2[[#This Row],[City]],"Country/region",TRUE)} -> #VALUE! | L6: =Table2[[#This Row],[Quantity]]*Table2[[#This Row],[Price]] -> 7404.3
B7: 10456 | C7: 44873 | D7: Chicken Sandwiches | E7: 9.95 | F7: In-store | G7: Credit Card | H7: Walter Muller | I7: 202 | J7: #VALUE! | K7: {=_FV(Table2[[#This Row],[City]],"Country/region",TRUE)} -> #VALUE! | L7: =Table2[[#This Row],[Quantity]]*Table2[[#This Row],[Price]] -> 2009.9
B8: 10457 | C8: 44873 | D8: Fries | E8: 3.49 | F8: In-store | G8: Credit Card | H8: Remy Monet | I8: 574 | J8: #VALUE! | K8: {=_FV(Table2[[#This Row],[City]],"Country/region",TRUE)} -> #VALUE! | L8: =Table2[[#This Row],[Quantity]]*Table2[[#This Row],[Price]] -> 2003.26
B9: 10457 | C9: 44873 | D9: Fries | E9: 3.49 | F9: In-store | G9: Credit Card | H9: Remy Monet | I9: 574 | J9: #VALUE! | K9: {=_FV(Table2[[#This Row],[City]],"Country/region",TRUE)} -> #VALUE! | L9: =Table2[[#This Row],[Quantity]]*Table2[[#This Row],[Price]] -> 2003.26 | O9: We start by fixing the "Manager" column where the names are formatted incorrectly. We fix this by using "=TRIM()" Function We then format the text into a value. (This will be a repeated step) .. Highlight the column (Ctrl + Shift + ↓) .. Copy the column (Ctrl + C) .. Paste as value (Alt + H + VV)
B10: 10459 | C10: 44873 | D10: Sides & Other | E10: 4.99 | F10: In-store | G10: Credit Card | H10: Walter Muller | I10: 201 | J10: #VALUE! | K10: {=_FV(Table2[[#This Row],[City]],"Country/region",TRUE)} -> #VALUE! | L10: =Table2[[#This Row],[Quantity]]*Table2[[#This Row],[Price]] -> 1002.99
B11: 10460 | C11: 44874 | D11: Burgers | E11: 12.99 | F11: In-store | G11: Credit Card | H11: Remy Monet | I11: 555 | J11: #VALUE! | K11: {=_FV(Table2[[#This Row],[City]],"Country/region",TRUE)} -> #VALUE! | L11: =Table2[[#This Row],[Quantity]]*Table2[[#This Row],[Price]] -> 7209.45
B12: 10461 | C12: 44874 | D12: Chicken Sandwiches | E12: 9.95 | F12: In-store | G12: Credit Card | H12: Remy Monet | I12: 202 | J12: #VALUE! | K12: {=_FV(Table2[[#This Row],[City]],"Country/region",TRUE)} -> #VALUE! | L12: =Table2[[#This Row],[Quantity]]*Table2[[#This Row],[Price]] -> 2009.9
B13: 10462 | C13: 44874 | D13: Fries | E13: 3.49 | F13: In-store | G13: Credit Card | H13: Remy Monet | I13: 574 | J13: #VALUE! | K13: {=_FV(Table2[[#This Row],[City]],"Country/region",TRUE)} -> #VALUE! | L13: =Table2[[#This Row],[Quantity]]*Table2[[#This Row],[Price]] -> 2003.26
B14: 10463 | C14: 44874 | D14: Beverages | E14: 2.95 | F14: In-store | G14: Credit Card | H14: Remy Monet | I14: 678 | J14: #VALUE! | K14: {=_FV(Table2[[#This Row],[City]],"Country/region",TRUE)} -> #VALUE! | L14: =Table2[[#This Row],[Quantity]]*Table2[[#This Row],[Price]] -> 2000.1
B15: 10464 | C15: 44874 | D15: Sides & Other | E15: 4.99 | F15: In-store | G15: Credit Card | H15: Remy Monet | I15: 201 | J15: #VALUE! | K15: {=_FV(Table2[[#This Row],[City]],"Country/region",TRUE)} -> #VALUE! | L15: =Table2[[#This Row],[Quantity]]*Table2[[#This Row],[Price]] -> 1002.99
B16: 10465 | C16: 44875 | D16: Burgers | E16: 12.99 | F16: In-store | G16: Credit Card | H16: Pablo Perez | I16: 555 | J16: #VALUE! | K16: {=_FV(Table2[[#This Row],[City]],"Country/region",TRUE)} -> #VALUE! | L16: =Table2[[#This Row],[Quantity]]*Table2[[#This Row],[Price]] -> 7209.45
B17: 10466 | C17: 44875 | D17: Chicken Sandwiches | E17: 9.95 | F17: In-store | G17: Credit Card | H17: Pablo Perez | I17: 202 | J17: #VALUE! | K17: {=_FV(Table2[[#This Row],[City]],"Country/region",TRUE)} -> #VALUE! | L17: =Table2[[#This Row],[Quantity]]*Table2[[#This Row],[Price]] -> 2009.9
B18: 10467 | C18: 44875 | D18: Fries | E18: 3.49 | F18: In-store | G18: Credit Card | H18: Pablo Perez | I18: 574 | J18: #VALUE! | K18: {=_FV(Table2[[#This Row],[City]],"Country/region",TRUE)} -> #VALUE! | L18: =Table2[[#This Row],[Quantity]]*Table2[[#This Row],[Price]] -> 2003.26
B19: 10468 | C19: 44875 | D19: Beverages | E19: 2.95 | F19: In-store | G19: Credit Card | H19: Pablo Perez | I19: 678 | J19: #VALUE! | K19: {=_FV(Table2[[#This Row],[City]],"Country/region",TRUE)} -> #VALUE! | L19: =Table2[[#This Row],[Quantity]]*Table2[[#This Row],[Price]] -> 2000.1
B20: 10468 | C20: 44875 | D20: Beverages | E20: 2.95 | F20: In-store | G20: Credit Card | H20: Pablo Perez | I20: 678 | J20: #VALUE! | K20: {=_FV(Table2[[#This Row],[City]],"Country/region",TRUE)} -> #VALUE! | L20: =Table2[[#This Row],[Quantity]]*Table2[[#This Row],[Price]] -> 2000.1 | O20: We move onto rounding up the "Quantity" as the decimal places don't make sense in context of the items Use "=ROUNDUP()" Specifically =(ROUNDUP([@Quantity],0)) it sets the value to the closest whole number
B21: 10470 | C21: 44876 | D21: Burgers | E21: 12.99 | F21: In-store | G21: Credit Card | H21: Pablo Perez | I21: 555 | J21: #VALUE! | K21: {=_FV(Table2[[#This Row],[City]],"Country/region",TRUE)} -> #VALUE! | L21: =Table2[[#This Row],[Quantity]]*Table2[[#This Row],[Price]] -> 7209.45
B22: 10471 | C22: 44876 | D22: Chicken Sandwiches | E22: 9.95 | F22: In-store | G22: Credit Card | H22: Pablo Perez | I22: 202 | J22: #VALUE! | K22: {=_FV(Table2[[#This Row],[City]],"Country/region",TRUE)} -> #VALUE! | L22: =Table2[[#This Row],[Quantity]]*Table2[[#This Row],[Price]] -> 2009.9
B23: 10472 | C23: 44876 | D23: Fries | E23: 3.49 | F23: In-store | G23: Credit Card | H23: Pablo Perez | I23: 631 | J23: #VALUE! | K23: {=_FV(Table2[[#This Row],[City]],"Country/region",TRUE)} -> #VALUE! | L23: =Table2[[#This Row],[Quantity]]*Table2[[#This Row],[Price]] -> 2202.19
B24: 10473 | C24: 44876 | D24: Beverages | E24: 2.95 | F24: In-store | G24: Credit Card | H24: Pablo Perez | I24: 678 | J24: #VALUE! | K24: {=_FV(Table2[[#This Row],[City]],"Country/region",TRUE)} -> #VALUE! | L24: =Table2[[#This Row],[Quantity]]*Table2[[#This Row],[Price]] -> 2000.1
B25: 10474 | C25: 44876 | D25: Sides & Other | E25: 4.99 | F25: In-store | G25: Credit Card | H25: Pablo Perez | I25: 201 | J25: #VALUE! | K25: {=_FV(Table2[[#This Row],[City]],"Country/region",TRUE)} -> #VALUE! | L25: =Table2[[#This Row],[Quantity]]*Table2[[#This Row],[Price]] -> 1002.99
B26: 10475 | C26: 44877 | D26: Burgers | E26: 12.99 | F26: In-store | G26: Credit Card | H26: Pablo Perez | I26: 524 | J26: #VALUE! | K26: {=_FV(Table2[[#This Row],[City]],"Country/region",TRUE)} -> #VALUE! | L26: =Table2[[#This Row],[Quantity]]*Table2[[#This Row],[Price]] -> 6806.76
B27: 10476 | C27: 44877 | D27: Chicken Sandwiches | E27: 9.95 | F27: In-store | G27: Credit Card | H27: Pablo Perez | I27: 202 | J27: #VALUE! | K27: {=_FV(Table2[[#This Row],[City]],"Country/region",TRUE)} -> #VALUE! | L27: =Table2[[#This Row],[Quantity]]*Table2[[#This Row],[Price]] -> 2009.9
B28: 10477 | C28: 44877 | D28: Fries | E28: 3.49 | F28: In-store | G28: Credit Card | H28: Pablo Perez | I28: 631 | J28: #VALUE! | K28: {=_FV(Table2[[#This Row],[City]],"Country/region",TRUE)} -> #VALUE! | L28: =Table2[[#This Row],[Quantity]]*Table2[[#This Row],[Price]] -> 2202.19
B29: 10478 | C29: 44877 | D29: Beverages | E29: 2.95 | F29: In-store | G29: Credit Card | H29: Pablo Perez | I29: 678 | J29: #VALUE! | K29: {=_FV(Table2[[#This Row],[City]],"Country/region",TRUE)} -> #VALUE! | L29: =Table2[[#This Row],[Quantity]]*Table2[[#This Row],[Price]] -> 2000.1 | O29: We can grab the country of the city by highlighting the column then going into the Data tab and selecting Geography
B30: 10479 | C30: 44877 | D30: Sides & Other | E30: 4.99 | F30: In-store | G30: Credit Card | H30: Pablo Perez | I30: 201 | J30: #VALUE! | K30: {=_FV(Table2[[#This Row],[City]],"Country/region",TRUE)} -> #VALUE! | L30: =Table2[[#This Row],[Quantity]]*Table2[[#This Row],[Price]] -> 1002.99
B31: 10480 | C31: 44878 | D31: Burgers | E31: 12.99 | F31: In-store | G31: Credit Card | H31: Pablo Perez | I31: 509 | J31: #VALUE! | K31: {=_FV(Table2[[#This Row],[City]],"Country/region",TRUE)} -> #VALUE! | L31: =Table2[[#This Row],[Quantity]]*Table2[[#This Row],[Price]] -> 6611.91
B32: 10481 | C32: 44878 | D32: Chicken Sandwiches | E32: 9.95 | F32: In-store | G32: Credit Card | H32: Pablo Perez | I32: 202 | J32: #VALUE! | K32: {=_FV(Table2[[#This Row],[City]],"Country/region",TRUE)} -> #VALUE! | L32: =Table2[[#This Row],[Quantity]]*Table2[[#This Row],[Price]] -> 2009.9
B33: 10482 | C33: 44878 | D33: Fries | E33: 25.5 | F33: In-store | G33: Credit Card | H33: Joao Silva | I33: 631 | J33: #VALUE! | K33: {=_FV(Table2[[#This Row],[City]],"Country/region",TRUE)} -> #VALUE! | L33: =Table2[[#This Row],[Quantity]]*Table2[[#This Row],[Price]] -> 16090.5 | O33: We can remove duplicate data sets by going into Data and selecting Remove Duplicates
B34: 10483 | C34: 44878 | D34: Beverages | E34: 33.22 | F34: In-store | G34: Credit Card | H34: Joao Silva | I34: 678 | J34: #VALUE! | K34: {=_FV(Table2[[#This Row],[City]],"Country/region",TRUE)} -> #VALUE! | L34: =Table2[[#This Row],[Quantity]]*Table2[[#This Row],[Price]] -> 22523.16
B35: 10484 | C35: 44878 | D35: Sides & Other | E35: 21.44 | F35: In-store | G35: Credit Card | H35: Joao Silva | I35: 201 | J35: #VALUE! | K35: {=_FV(Table2[[#This Row],[City]],"Country/region",TRUE)} -> #VALUE! | L35: =Table2[[#This Row],[Quantity]]*Table2[[#This Row],[Price]] -> 4309.44
B36: 10485 | C36: 44879 | D36: Burgers | E36: 27.99 | F36: In-store | G36: Credit Card | H36: Joao Silva | I36: 524 | J36: #VALUE! | K36: {=_FV(Table2[[#This Row],[City]],"Country/region",TRUE)} -> #VALUE! | L36: =Table2[[#This Row],[Quantity]]*Table2[[#This Row],[Price]] -> 14666.76
B37: 10486 | C37: 44879 | D37: Chicken Sandwiches | E37: 29.05 | F37: In-store | G37: Credit Card | H37: Joao Silva | I37: 202 | J37: #VALUE! | K37: {=_FV(Table2[[#This Row],[City]],"Country/region",TRUE)} -> #VALUE! | L37: =Table2[[#This Row],[Quantity]]*Table2[[#This Row],[Price]] -> 5868.1
B38: 10487 | C38: 44879 | D38: Fries | E38: 3.49 | F38: In-store | G38: Credit Card | H38: Joao Silva | I38: 631 | J38: #VALUE! | K38: {=_FV(Table2[[#This Row],[City]],"Country/region",TRUE)} -> #VALUE! | L38: =Table2[[#This Row],[Quantity]]*Table2[[#This Row],[Price]] -> 2202.19
B39: 10488 | C39: 44879 | D39: Beverages | E39: 2.95 | F39: In-store | G39: Credit Card | H39: Joao Silva | I39: 678 | J39: #VALUE! | K39: {=_FV(Table2[[#This Row],[City]],"Country/region",TRUE)} -> #VALUE! | L39: =Table2[[#This Row],[Quantity]]*Table2[[#This Row],[Price]] -> 2000.1 | O39: Price | R39: I was able to create this whole table by using the Excel add-in "Data Analysis" I used Descriptive Statistics on the price column and selected the summary statistics to produce a table with all the necessary information
B40: 10489 | C40: 44879 | D40: Sides & Other | E40: 4.99 | F40: In-store | G40: Credit Card | H40: Pablo Perez | I40: 201 | J40: #VALUE! | K40: {=_FV(Table2[[#This Row],[City]],"Country/region",TRUE)} -> #VALUE! | L40: =Table2[[#This Row],[Quantity]]*Table2[[#This Row],[Price]] -> 1002.99
B41: 10490 | C41: 44880 | D41: Burgers | E41: 12.99 | F41: In-store | G41: Credit Card | H41: Pablo Perez | I41: 509 | J41: #VALUE! | K41: {=_FV(Table2[[#This Row],[City]],"Country/region",TRUE)} -> #VALUE! | L41: =Table2[[#This Row],[Quantity]]*Table2[[#This Row],[Price]] -> 6611.91 | O41: Mean | P41: 7.2691221
B42: 10491 | C42: 44880 | D42: Chicken Sandwiches | E42: 9.95 | F42: In-store | G42: Credit Card | H42: Pablo Perez | I42: 202 | J42: #VALUE! | K42: {=_FV(Table2[[#This Row],[City]],"Country/region",TRUE)} -> #VALUE! | L42: =Table2[[#This Row],[Quantity]]*Table2[[#This Row],[Price]] -> 2009.9 | O42: Standard Error | P42: 0.29992326
B43: 10492 | C43: 44880 | D43: Fries | E43: 3.49 | F43: In-store | G43: Credit Card | H43: Pablo Perez | I43: 574 | J43: #VALUE! | K43: {=_FV(Table2[[#This Row],[City]],"Country/region",TRUE)} -> #VALUE! | L43: =Table2[[#This Row],[Quantity]]*Table2[[#This Row],[Price]] -> 2003.26 | O43: Median | P43: 4.99
B44: 10493 | C44: 44880 | D44: Beverages | E44: 2.95 | F44: In-store | G44: Credit Card | H44: Pablo Perez | I44: 678 | J44: #VALUE! | K44: {=_FV(Table2[[#This Row],[City]],"Country/region",TRUE)} -> #VALUE! | L44: =Table2[[#This Row],[Quantity]]*Table2[[#This Row],[Price]] -> 2000.1 | O44: Mode | P44: 3.49
B45: 10494 | C45: 44880 | D45: Sides & Other | E45: 4.99 | F45: In-store | G45: Credit Card | H45: Pablo Perez | I45: 201 | J45: #VALUE! | K45: {=_FV(Table2[[#This Row],[City]],"Country/region",TRUE)} -> #VALUE! | L45: =Table2[[#This Row],[Quantity]]*Table2[[#This Row],[Price]] -> 1002.99 | O45: Standard Deviation | P45: 4.854682
B46: 10495 | C46: 44881 | D46: Burgers | E46: 12.99 | F46: In-store | G46: Credit Card | H46: Pablo Perez | I46: 509 | J46: #VALUE! | K46: {=_FV(Table2[[#This Row],[City]],"Country/region",TRUE)} -> #VALUE! | L46: =Table2[[#This Row],[Quantity]]*Table2[[#This Row],[Price]] -> 6611.91 | O46: Sample Variance | P46: 23.567938
B47: 10496 | C47: 44881 | D47: Chicken Sandwiches | E47: 9.95 | F47: In-store | G47: Credit Card | H47: Pablo Perez | I47: 202 | J47: #VALUE! | K47: {=_FV(Table2[[#This Row],[City]],"Country/region",TRUE)} -> #VALUE! | L47: =Table2[[#This Row],[Quantity]]*Table2[[#This Row],[Price]] -> 2009.9 | O47: Kurtosis | P47: 4.7442878
B48: 10497 | C48: 44881 | D48: Fries | E48: 3.49 | F48: In-store | G48: Credit Card | H48: Pablo Perez | I48: 574 | J48: #VALUE! | K48: {=_FV(Table2[[#This Row],[City]],"Country/region",TRUE)} -> #VALUE! | L48: =Table2[[#This Row],[Quantity]]*Table2[[#This Row],[Price]] -> 2003.26 | O48: Skewness | P48: 1.6447758
B49: 10498 | C49: 44881 | D49: Beverages | E49: 2.95 | F49: Drive-thru | G49: Credit Card | H49: Pablo Perez | I49: 678 | J49: #VALUE! | K49: {=_FV(Table2[[#This Row],[City]],"Country/region",TRUE)} -> #VALUE! | L49: =Table2[[#This Row],[Quantity]]*Table2[[#This Row],[Price]] -> 2000.1 | O49: Range | P49: 30.27
B50: 10499 | C50: 44881 | D50: Sides & Other | E50: 4.99 | F50: Drive-thru | G50: Credit Card | H50: Pablo Perez | I50: 201 | J50: #VALUE! | K50: {=_FV(Table2[[#This Row],[City]],"Country/region",TRUE)} -> #VALUE! | L50: =Table2[[#This Row],[Quantity]]*Table2[[#This Row],[Price]] -> 1002.99 | O50: Minimum | P50: 2.95
B51: 10500 | C51: 44882 | D51: Burgers | E51: 12.99 | F51: Drive-thru | G51: Credit Card | H51: Pablo Perez | I51: 524 | J51: #VALUE! | K51: {=_FV(Table2[[#This Row],[City]],"Country/region",TRUE)} -> #VALUE! | L51: =Table2[[#This Row],[Quantity]]*Table2[[#This Row],[Price]] -> 6806.76 | O51: Maximum | P51: 33.22
B52: 10501 | C52: 44882 | D52: Chicken Sandwiches | E52: 9.95 | F52: Drive-thru | G52: Credit Card | H52: Pablo Perez | I52: 202 | J52: #VALUE! | K52: {=_FV(Table2[[#This Row],[City]],"Country/region",TRUE)} -> #VALUE! | L52: =Table2[[#This Row],[Quantity]]*Table2[[#This Row],[Price]] -> 2009.9 | O52: Sum | P52: 1904.51
B53: 10502 | C53: 44882 | D53: Fries | E53: 3.49 | F53: Drive-thru | G53: Credit Card | H53: Pablo Perez | I53: 631 | J53: #VALUE! | K53: {=_FV(Table2[[#This Row],[City]],"Country/region",TRUE)} -> #VALUE! | L53: =Table2[[#This Row],[Quantity]]*Table2[[#This Row],[Price]] -> 2202.19 | O53: Count | P53: 262
B54: 10503 | C54: 44882 | D54: Beverages | E54: 2.95 | F54: Drive-thru | G54: Credit Card | H54: Pablo Perez | I54: 678 | J54: #VALUE! | K54: {=_FV(Table2[[#This Row],[City]],"Country/region",TRUE)} -> #VALUE! | L54: =Table2[[#This Row],[Quantity]]*Table2[[#This Row],[Price]] -> 2000.1
B55: 10504 | C55: 44882 | D55: Sides & Other | E55: 4.99 | F55: Drive-thru | G55: Credit Card | H55: Pablo Perez | I55: 201 | J55: #VALUE! | K55: {=_FV(Table2[[#This Row],[City]],"Country/region",TRUE)} -> #VALUE! | L55: =Table2[[#This Row],[Quantity]]*Table2[[#This Row],[Price]] -> 1002.99
B56: 10505 | C56: 44883 | D56: Burgers | E56: 12.99 | F56: Drive-thru | G56: Credit Card | H56: Pablo Perez | I56: 539 | J56: #VALUE! | K56: {=_FV(Table2[[#This Row],[City]],"Country/region",TRUE)} -> #VALUE! | L56: =Table2[[#This Row],[Quantity]]*Table2[[#This Row],[Price]] -> 7001.61
B57: 10506 | C57: 44883 | D57: Chicken Sandwiches | E57: 9.95 | F57: Drive-thru | G57: Credit Card | H57: Pablo Perez | I57: 202 | J57: #VALUE! | K57: {=_FV(Table2[[#This Row],[City]],"Country/region",TRUE)} -> #VALUE! | L57: =Table2[[#This Row],[Quantity]]*Table2[[#This Row],[Price]] -> 2009.9
B58: 10507 | C58: 44883 | D58: Fries | E58: 3.49 | F58: Drive-thru | G58: Credit Card | H58: Pablo Perez | I58: 688 | J58: #VALUE! | K58: {=_FV(Table2[[#This Row],[City]],"Country/region",TRUE)} -> #VALUE! | L58: =Table2[[#This Row],[Quantity]]*Table2[[#This Row],[Price]] -> 2401.12
B59: 10508 | C59: 44883 | D59: Beverages | E59: 2.95 | F59: Drive-thru | G59: Credit Card | H59: Pablo Perez | I59: 678 | J59: #VALUE! | K59: {=_FV(Table2[[#This Row],[City]],"Country/region",TRUE)} -> #VALUE! | L59: =Table2[[#This Row],[Quantity]]*Table2[[#This Row],[Price]] -> 2000.1
B60: 10509 | C60: 44883 | D60: Sides & Other | E60: 4.99 | F60: Drive-thru | G60: Credit Card | H60: Pablo Perez | I60: 201 | J60: #VALUE! | K60: {=_FV(Table2[[#This Row],[City]],"Country/region",TRUE)} -> #VALUE! | L60: =Table2[[#This Row],[Quantity]]*Table2[[#This Row],[Price]] -> 1002.99
B61: 10510 | C61: 44884 | D61: Burgers | E61: 12.99 | F61: Drive-thru | G61: Credit Card | H61: Pablo Perez | I61: 509 | J61: #VALUE! | K61: {=_FV(Table2[[#This Row],[City]],"Country/region",TRUE)} -> #VALUE! | L61: =Table2[[#This Row],[Quantity]]*Table2[[#This Row],[Price]] -> 6611.91
B62: 10511 | C62: 44884 | D62: Chicken Sandwiches | E62: 9.95 | F62: Drive-thru | G62: Credit Card | H62: Joao Silva | I62: 202 | J62: #VALUE! | K62: {=_FV(Table2[[#This Row],[City]],"Country/region",TRUE)} -> #VALUE! | L62: =Table2[[#This Row],[Quantity]]*Table2[[#This Row],[Price]] -> 2009.9
B63: 10512 | C63: 44884 | D63: Fries | E63: 3.49 | F63: Drive-thru | G63: Credit Card | H63: Joao Silva | I63: 688 | J63: #VALUE! | K63: {=_FV(Table2[[#This Row],[City]],"Country/region",TRUE)} -> #VALUE! | L63: =Table2[[#This Row],[Quantity]]*Table2[[#This Row],[Price]] -> 2401.12 | O63: Quantity
B64: 10513 | C64: 44884 | D64: Beverages | E64: 2.95 | F64: Drive-thru | G64: Cash | H64: Joao Silva | I64: 678 | J64: #VALUE! | K64: {=_FV(Table2[[#This Row],[City]],"Country/region",TRUE)} -> #VALUE! | L64: =Table2[[#This Row],[Quantity]]*Table2[[#This Row],[Price]] -> 2000.1
B65: 10514 | C65: 44884 | D65: Sides & Other | E65: 4.99 | F65: Drive-thru | G65: Cash | H65: Joao Silva | I65: 201 | J65: #VALUE! | K65: {=_FV(Table2[[#This Row],[City]],"Country/region",TRUE)} -> #VALUE! | L65: =Table2[[#This Row],[Quantity]]*Table2[[#This Row],[Price]] -> 1002.99 | O65: Mean | P65: 7.2691221
B66: 10515 | C66: 44885 | D66: Burgers | E66: 12.99 | F66: Drive-thru | G66: Cash | H66: Joao Silva | I66: 478 | J66: #VALUE! | K66: {=_FV(Table2[[#This Row],[City]],"Country/region",TRUE)} -> #VALUE! | L66: =Table2[[#This Row],[Quantity]]*Table2[[#This Row],[Price]] -> 6209.22 | O66: Standard Error | P66: 0.29992326
B67: 10516 | C67: 44885 | D67: Chicken Sandwiches | E67: 9.95 | F67: Drive-thru | G67: Cash | H67: Joao Silva | I67: 202 | J67: #VALUE! | K67: {=_FV(Table2[[#This Row],[City]],"Country/region",TRUE)} -> #VALUE! | L67: =Table2[[#This Row],[Quantity]]*Table2[[#This Row],[Price]] -> 2009.9 | O67: Median | P67: 4.99
B68: 10483 | C68: 44878 | D68: Beverages | E68: 2.95 | F68: In-store | G68: Credit Card | H68: Joao Silva | I68: 678 | J68: #VALUE! | K68: {=_FV(Table2[[#This Row],[City]],"Country/region",TRUE)} -> #VALUE! | L68: =Table2[[#This Row],[Quantity]]*Table2[[#This Row],[Price]] -> 2000.1 | O68: Mode | P68: 3.49
B69: 10484 | C69: 44878 | D69: Sides & Other | E69: 4.99 | F69: In-store | G69: Credit Card | H69: Joao Silva | I69: 201 | J69: #VALUE! | K69: {=_FV(Table2[[#This Row],[City]],"Country/region",TRUE)} -> #VALUE! | L69: =Table2[[#This Row],[Quantity]]*Table2[[#This Row],[Price]] -> 1002.99 | O69: Standard Deviation | P69: 4.854682
B70: 10485 | C70: 44879 | D70: Burgers | E70: 12.99 | F70: In-store | G70: Credit Card | H70: Joao Silva | I70: 524 | J70: #VALUE! | K70: {=_FV(Table2[[#This Row],[City]],"Country/region",TRUE)} -> #VALUE! | L70: =Table2[[#This Row],[Quantity]]*Table2[[#This Row],[Price]] -> 6806.76 | O70: Sample Variance | P70: 23.567938
B71: 10520 | C71: 44886 | D71: Burgers | E71: 12.99 | F71: Drive-thru | G71: Cash | H71: Remy Monet | I71: 493 | J71: #VALUE! | K71: {=_FV(Table2[[#This Row],[City]],"Country/region",TRUE)} -> #VALUE! | L71: =Table2[[#This Row],[Quantity]]*Table2[[#This Row],[Price]] -> 6404.07 | O71: Kurtosis | P71: 4.7442878
B72: 10521 | C72: 44886 | D72: Chicken Sandwiches | E72: 9.95 | F72: Drive-thru | G72: Cash | H72: Remy Monet | I72: 202 | J72: #VALUE! | K72: {=_FV(Table2[[#This Row],[City]],"Country/region",TRUE)} -> #VALUE! | L72: =Table2[[#This Row],[Quantity]]*Table2[[#This Row],[Price]] -> 2009.9 | O72: Skewness | P72: 1.6447758
B73: 10522 | C73: 44886 | D73: Fries | E73: 3.49 | F73: Drive-thru | G73: Cash | H73: Remy Monet | I73: 688 | J73: #VALUE! | K73: {=_FV(Table2[[#This Row],[City]],"Country/region",TRUE)} -> #VALUE! | L73: =Table2[[#This Row],[Quantity]]*Table2[[#This Row],[Price]] -> 2401.12 | O73: Range | P73: 30.27
B74: 10523 | C74: 44886 | D74: Beverages | E74: 2.95 | F74: Drive-thru | G74: Cash | H74: Remy Monet | I74: 746 | J74: #VALUE! | K74: {=_FV(Table2[[#This Row],[City]],"Country/region",TRUE)} -> #VALUE! | L74: =Table2[[#This Row],[Quantity]]*Table2[[#This Row],[Price]] -> 2200.7 | O74: Minimum | P74: 2.95
B75: 10524 | C75: 44886 | D75: Sides & Other | E75: 4.99 | F75: Drive-thru | G75: Cash | H75: Remy Monet | I75: 201 | J75: #VALUE! | K75: {=_FV(Table2[[#This Row],[City]],"Country/region",TRUE)} -> #VALUE! | L75: =Table2[[#This Row],[Quantity]]*Table2[[#This Row],[Price]] -> 1002.99 | O75: Maximum | P75: 33.22
B76: 10525 | C76: 44887 | D76: Burgers | E76: 12.99 | F76: Drive-thru | G76: Cash | H76: Remy Monet | I76: 462 | J76: #VALUE! | K76: {=_FV(Table2[[#This Row],[City]],"Country/region",TRUE)} -> #VALUE! | L76: =Table2[[#This Row],[Quantity]]*Table2[[#This Row],[Price]] -> 6001.38 | O76: Sum | P76: 1904.51
B77: 10526 | C77: 44887 | D77: Chicken Sandwiches | E77: 9.95 | F77: Drive-thru | G77: Cash | H77: Remy Monet | I77: 202 | J77: #VALUE! | K77: {=_FV(Table2[[#This Row],[City]],"Country/region",TRUE)} -> #VALUE! | L77: =Table2[[#This Row],[Quantity]]*Table2[[#This Row],[Price]] -> 2009.9 | O77: Count | P77: 262
B78: 10527 | C78: 44887 | D78: Fries | E78: 3.49 | F78: Drive-thru | G78: Cash | H78: Remy Monet | I78: 688 | J78: #VALUE! | K78: {=_FV(Table2[[#This Row],[City]],"Country/region",TRUE)} -> #VALUE! | L78: =Table2[[#This Row],[Quantity]]*Table2[[#This Row],[Price]] -> 2401.12
B79: 10528 | C79: 44887 | D79: Beverages | E79: 2.95 | F79: Drive-thru | G79: Cash | H79: Remy Monet | I79: 746 | J79: #VALUE! | K79: {=_FV(Table2[[#This Row],[City]],"Country/region",TRUE)} -> #VALUE! | L79: =Table2[[#This Row],[Quantity]]*Table2[[#This Row],[Price]] -> 2200.7
B80: 10529 | C80: 44887 | D80: Sides & Other | E80: 4.99 | F80: Drive-thru | G80: Cash | H80: Remy Monet | I80: 201 | J80: #VALUE! | K80: {=_FV(Table2[[#This Row],[City]],"Country/region",TRUE)} -> #VALUE! | L80: =Table2[[#This Row],[Quantity]]*Table2[[#This Row],[Price]] -> 1002.99
B81: 10530 | C81: 44888 | D81: Burgers | E81: 12.99 | F81: Drive-thru | G81: Cash | H81: Remy Monet | I81: 478 | J81: #VALUE! | K81: {=_FV(Table2[[#This Row],[City]],"Country/region",TRUE)} -> #VALUE! | L81: =Table2[[#This Row],[Quantity]]*Table2[[#This Row],[Price]] -> 6209.22
B82: 10531 | C82: 44888 | D82: Chicken Sandwiches | E82: 9.95 | F82: Drive-thru | G82: Cash | H82: Remy Monet | I82: 202 | J82: #VALUE! | K82: {=_FV(Table2[[#This Row],[City]],"Country/region",TRUE)} -> #VALUE! | L82: =Table2[[#This Row],[Quantity]]*Table2[[#This Row],[Price]] -> 2009.9
B83: 10532 | C83: 44888 | D83: Fries | E83: 3.49 | F83: Drive-thru | G83: Cash | H83: Joao Silva | I83: 688 | J83: #VALUE! | K83: {=_FV(Table2[[#This Row],[City]],"Country/region",TRUE)} -> #VALUE! | L83: =Table2[[#This Row],[Quantity]]*Table2[[#This Row],[Price]] -> 2401.12
B84: 10533 | C84: 44888 | D84: Beverages | E84: 2.95 | F84: Drive-thru | G84: Cash | H84: Joao Silva | I84: 746 | J84: #VALUE! | K84: {=_FV(Table2[[#This Row],[City]],"Country/region",TRUE)} -> #VALUE! | L84: =Table2[[#This Row],[Quantity]]*Table2[[#This Row],[Price]] -> 2200.7
B85: 10534 | C85: 44888 | D85: Sides & Other | E85: 4.99 | F85: Drive-thru | G85: Cash | H85: Pablo Perez | I85: 201 | J85: #VALUE! | K85: {=_FV(Table2[[#This Row],[City]],"Country/region",TRUE)} -> #VALUE! | L85: =Table2[[#This Row],[Quantity]]*Table2[[#This Row],[Price]] -> 1002.99
B86: 10535 | C86: 44889 | D86: Burgers | E86: 12.99 | F86: Drive-thru | G86: Credit Card | H86: Pablo Perez | I86: 478 | J86: #VALUE! | K86: {=_FV(Table2[[#This Row],[City]],"Country/region",TRUE)} -> #VALUE! | L86: =Table2[[#This Row],[Quantity]]*Table2[[#This Row],[Price]] -> 6209.22
B87: 10536 | C87: 44889 | D87: Chicken Sandwiches | E87: 9.95 | F87: Drive-thru | G87: Credit Card | H87: Pablo Perez | I87: 202 | J87: #VALUE! | K87: {=_FV(Table2[[#This Row],[City]],"Country/region",TRUE)} -> #VALUE! | L87: =Table2[[#This Row],[Quantity]]*Table2[[#This Row],[Price]] -> 2009.9
B88: 10537 | C88: 44889 | D88: Fries | E88: 3.49 | F88: Drive-thru | G88: Credit Card | H88: Pablo Perez | I88: 631 | J88: #VALUE! | K88: {=_FV(Table2[[#This Row],[City]],"Country/region",TRUE)} -> #VALUE! | L88: =Table2[[#This Row],[Quantity]]*Table2[[#This Row],[Price]] -> 2202.19
B89: 10538 | C89: 44889 | D89: Beverages | E89: 2.95 | F89: Drive-thru | G89: Credit Card | H89: Pablo Perez | I89: 746 | J89: #VALUE! | K89: {=_FV(Table2[[#This Row],[City]],"Country/region",TRUE)} -> #VALUE! | L89: =Table2[[#This Row],[Quantity]]*Table2[[#This Row],[Price]] -> 2200.7
... B93: 10542 | C93: 44890 | D93: Fries | E93: 3.49 | F93: Drive-thru | G93: Credit Card | H93: Tom Jackson | I93: 631 | J93: #VALUE! | K93: {=_FV(Table2[[#This Row],[City]],"Country/region",TRUE)} -> #VALUE! | L93: =Table2[[#This Row],[Quantity]]*Table2[[#This Row],[Price]] -> 2202.19
B94: 10543 | C94: 44890 | D94: Beverages | E94: 2.95 | F94: Drive-thru | G94: Credit Card | H94: Tom Jackson | I94: 746 | J94: #VALUE! | K94: {=_FV(Table2[[#This Row],[City]],"Country/region",TRUE)} -> #VALUE! | L94: =Table2[[#This Row],[Quantity]]*Table2[[#This Row],[Price]] -> 2200.7 | O94: This chart allows us to look at the data of the price column and see who could possibly be inputting their data incorrectly. Changing the X axis data to be the managers name allows us to identify that Joao Silva could be having issues with incorrect data entries
B95: 10544 | C95: 44890 | D95: Sides & Other | E95: 4.99 | F95: Drive-thru | G95: Credit Card | H95: Tom Jackson | I95: 201 | J95: #VALUE! | K95: {=_FV(Table2[[#This Row],[City]],"Country/region",TRUE)} -> #VALUE! | L95: =Table2[[#This Row],[Quantity]]*Table2[[#This Row],[Price]] -> 1002.99
B96: 10545 | C96: 44891 | D96: Burgers | E96: 12.99 | F96: Drive-thru | G96: Credit Card | H96: Tom Jackson | I96: 447 | J96: #VALUE! | K96: {=_FV(Table2[[#This Row],[City]],"Country/region",TRUE)} -> #VALUE! | L96: =Table2[[#This Row],[Quantity]]*Table2[[#This Row],[Price]] -> 5806.53
B97: 10546 | C97: 44891 | D97: Chicken Sandwiches | E97: 9.95 | F97: Drive-thru | G97: Credit Card | H97: Tom Jackson | I97: 202 | J97: #VALUE! | K97: {=_FV(Table2[[#This Row],[City]],"Country/region",TRUE)} -> #VALUE! | L97: =Table2[[#This Row],[Quantity]]*Table2[[#This Row],[Price]] -> 2009.9
B98: 10547 | C98: 44891 | D98: Fries | E98: 3.49 | F98: Drive-thru | G98: Credit Card | H98: Tom Jackson | I98: 631 | J98: #VALUE! | K98: {=_FV(Table2[[#This Row],[City]],"Country/region",TRUE)} -> #VALUE! | L98: =Table2[[#This Row],[Quantity]]*Table2[[#This Row],[Price]] -> 2202.19
B99: 10548 | C99: 44891 | D99: Beverages | E99: 2.95 | F99: Drive-thru | G99: Credit Card | H99: Tom Jackson | I99: 746 | J99: #VALUE! | K99: {=_FV(Table2[[#This Row],[City]],"Country/region",TRUE)} -> #VALUE! | L99: =Table2[[#This Row],[Quantity]]*Table2[[#This Row],[Price]] -> 2200.7
B100: 10549 | C100: 44891 | D100: Sides & Other | E100: 4.99 | F100: Drive-thru | G100: Credit Card | H100: Tom Jackson | I100: 201 | J100: #VALUE! | K100: {=_FV(Table2[[#This Row],[City]],"Country/region",TRUE)} -> #VALUE! | L100: =Table2[[#This Row],[Quantity]]*Table2[[#This Row],[Price]] -> 1002.99
B101: 10550 | C101: 44892 | D101: Burgers | E101: 12.99 | F101: Drive-thru | G101: Credit Card | H101: Tom Jackson | I101: 462 | J101: #VALUE! | K101: {=_FV(Table2[[#This Row],[City]],"Country/region",TRUE)} -> #VALUE! | L101: =Table2[[#This Row],[Quantity]]*Table2[[#This Row],[Price]] -> 6001.38 | O101: Going into analysis we need to answer 3 questions which is the next step in the process
B102: 10551 | C102: 44892 | D102: Chicken Sandwiches | E102: 9.95 | F102: Drive-thru | G102: Credit Card | H102: Tom Jackson | I102: 202 | J102: #VALUE! | K102: {=_FV(Table2[[#This Row],[City]],"Country/region",TRUE)} -> #VALUE! | L102: =Table2[[#This Row],[Quantity]]*Table2[[#This Row],[Price]] -> 2009.9
B103: 10552 | C103: 44892 | D103: Fries | E103: 3.49 | F103: Online | G103: Credit Card | H103: Tom Jackson | I103: 631 | J103: #VALUE! | K103: {=_FV(Table2[[#This Row],[City]],"Country/region",TRUE)} -> #VALUE! | L103: =Table2[[#This Row],[Quantity]]*Table2[[#This Row],[Price]] -> 2202.19
B104: 10553 | C104: 44892 | D104: Beverages | E104: 2.95 | F104: Online | G104: Credit Card | H104: Tom Jackson | I104: 746 | J104: #VALUE! | K104: {=_FV(Table2[[#This Row],[City]],"Country/region",TRUE)} -> #VALUE! | L104: =Table2[[#This Row],[Quantity]]*Table2[[#This Row],[Price]] -> 2200.7
...

Sheet Clean
B2: Order ID | C2: Date | D2: Product | E2: Price | F2: Quantity | G2: Cost | H2: City | I2: Country | J2: Purchase Type | K2: Payment Method | L2: Manager | M2: Revenue
B3: 10452 | C3: 44872 | D3: Fries | E3: 3.49 | F3: 574 | G3: 0.88 | H3: #VALUE! | I3: {=_FV(H3,"Country/region",TRUE)} -> #VALUE! | J3: Online | K3: Gift Card | L3: Tom Jackson | M3: =Table1[[#This Row],[Price]]*Table1[[#This Row],[Quantity]] -> 2003.26
B4: 10453 | C4: 44872 | D4: Beverages | E4: 2.95 | F4: 746 | G4: 0.47 | H4: #VALUE! | I4: {=_FV(H4,"Country/region",TRUE)} -> #VALUE! | J4: Online | K4: Gift Card | L4: Pablo Perez | M4: =Table1[[#This Row],[Price]]*Table1[[#This Row],[Quantity]] -> 2200.7
B5: 10454 | C5: 44872 | D5: Sides & Other | E5: 4.99 | F5: 201 | G5: 2.25 | H5: #VALUE! | I5: {=_FV(H5,"Country/region",TRUE)} -> #VALUE! | J5: In-store | K5: Gift Card | L5: Joao Silva | M5: =Table1[[#This Row],[Price]]*Table1[[#This Row],[Quantity]] -> 1002.99
B6: 10455 | C6: 44873 | D6: Burgers | E6: 12.99 | F6: 570 | G6: 4.32 | H6: #VALUE! | I6: {=_FV(H6,"Country/region",TRUE)} -> #VALUE! | J6: In-store | K6: Credit Card | L6: Walter Muller | M6: =Table1[[#This Row],[Price]]*Table1[[#This Row],[Quantity]] -> 7404.3
B7: 10456 | C7: 44873 | D7: Chicken Sandwiches | E7: 9.95 | F7: 202 | G7: 2.85 | H7: #VALUE! | I7: {=_FV(H7,"Country/region",TRUE)} -> #VALUE! | J7: In-store | K7: Credit Card | L7: Walter Muller | M7: =Table1[[#This Row],[Price]]*Table1[[#This Row],[Quantity]] -> 2009.9
B8: 10457 | C8: 44873 | D8: Fries | E8: 3.49 | F8: 574 | G8: 0.88 | H8: #VALUE! | I8: {=_FV(H8,"Country/region",TRUE)} -> #VALUE! | J8: In-store | K8: Credit Card | L8: Remy Monet | M8: =Table1[[#This Row],[Price]]*Table1[[#This Row],[Quantity]] -> 2003.26
B9: 10459 | C9: 44873 | D9: Sides & Other | E9: 4.99 | F9: 201 | G9: 2.25 | H9: #VALUE! | I9: {=_FV(H9,"Country/region",TRUE)} -> #VALUE! | J9: In-store | K9: Credit Card | L9: Remy Monet | M9: =Table1[[#This Row],[Price]]*Table1[[#This Row],[Quantity]] -> 1002.99
B10: 10460 | C10: 44874 | D10: Burgers | E10: 12.99 | F10: 555 | G10: 4.32 | H10: #VALUE! | I10: {=_FV(H10,"Country/region",TRUE)} -> #VALUE! | J10: In-store | K10: Credit Card | L10: Walter Muller | M10: =Table1[[#This Row],[Price]]*Table1[[#This Row],[Quantity]] -> 7209.45
B11: 10461 | C11: 44874 | D11: Chicken Sandwiches | E11: 9.95 | F11: 202 | G11: 2.85 | H11: #VALUE! | I11: {=_FV(H11,"Country/region",TRUE)} -> #VALUE! | J11: In-store | K11: Credit Card | L11: Remy Monet | M11: =Table1[[#This Row],[Price]]*Table1[[#This Row],[Quantity]] -> 2009.9
B12: 10462 | C12: 44874 | D12: Fries | E12: 3.49 | F12: 574 | G12: 0.88 | H12: #VALUE! | I12: {=_FV(H12,"Country/region",TRUE)} -> #VALUE! | J12: In-store | K12: Credit Card | L12: Remy Monet | M12: =Table1[[#This Row],[Price]]*Table1[[#This Row],[Quantity]] -> 2003.26
B13: 10463 | C13: 44874 | D13: Beverages | E13: 2.95 | F13: 678 | G13: 0.47 | H13: #VALUE! | I13: {=_FV(H13,"Country/region",TRUE)} -> #VALUE! | J13: In-store | K13: Credit Card | L13: Remy Monet | M13: =Table1[[#This Row],[Price]]*Table1[[#This Row],[Quantity]] -> 2000.1
B14: 10464 | C14: 44874 | D14: Sides & Other | E14: 4.99 | F14: 201 | G14: 2.25 | H14: #VALUE! | I14: {=_FV(H14,"Country/region",TRUE)} -> #VALUE! | J14: In-store | K14: Credit Card | L14: Remy Monet | M14: =Table1[[#This Row],[Price]]*Table1[[#This Row],[Quantity]] -> 1002.99
... B256: 10713 | C256: 44924 | D256: Beverages | E256: 2.95 | F256: 678 | G256: 0.47 | H256: #VALUE! | I256: {=_FV(H256,"Country/region",TRUE)} -> #VALUE! | J256: Drive-thru | K256: Gift Card | L256: Walter Muller | M256: =Table1[[#This Row],[Price]]*Table1[[#This Row],[Quantity]] -> 2000.1

Sheet Detail1
A1: Details for Sum of Revenue
A3: Order ID | B3: Date | C3: Product | D3: Price | E3: Purchase Type | F3: Payment Method | G3: Manager | H3: Quantity | I3: City | J3: Country/region | K3: Revenue
A4: 10452 | B4: 44872 | C4: Fries | D4: 3.49 | E4: Online | F4: Gift Card | G4: Tom Jackson | H4: 574 | I4: #VALUE! | J4: #VALUE! | K4: 2003.26
A5: 10453 | B5: 44872 | C5: Beverages | D5: 2.95 | E5: Online | F5: Gift Card | G5: Pablo Perez | H5: 746 | I5: #VALUE! | J5: #VALUE! | K5: 2200.7
A6: 10454 | B6: 44872 | C6: Sides & Other | D6: 4.99 | E6: In-store | F6: Gift Card | G6: Joao Silva | H6: 201 | I6: #VALUE! | J6: #VALUE! | K6: 1002.99
A7: 10455 | B7: 44873 | C7: Burgers | D7: 12.99 | E7: In-store | F7: Credit Card | G7: Walter Muller | H7: 570 | I7: #VALUE! | J7: #VALUE! | K7: 7404.3
A8: 10456 | B8: 44873 | C8: Chicken Sandwiches | D8: 9.95 | E8: In-store | F8: Credit Card | G8: Walter Muller | H8: 202 | I8: #VALUE! | J8: #VALUE! | K8: 2009.9
A9: 10457 | B9: 44873 | C9: Fries | D9: 3.49 | E9: In-store | F9: Credit Card | G9: Remy Monet | H9: 574 | I9: #VALUE! | J9: #VALUE! | K9: 2003.26
A10: 10457 | B10: 44873 | C10: Fries | D10: 3.49 | E10: In-store | F10: Credit Card | G10: Remy Monet | H10: 574 | I10: #VALUE! | J10: #VALUE! | K10: 2003.26
A11: 10459 | B11: 44873 | C11: Sides & Other | D11: 4.99 | E11: In-store | F11: Credit Card | G11: Walter Muller | H11: 201 | I11: #VALUE! | J11: #VALUE! | K11: 1002.99
A12: 10460 | B12: 44874 | C12: Burgers | D12: 12.99 | E12: In-store | F12: Credit Card | G12: Remy Monet | H12: 555 | I12: #VALUE! | J12: #VALUE! | K12: 7209.45
A13: 10461 | B13: 44874 | C13: Chicken Sandwiches | D13: 9.95 | E13: In-store | F13: Credit Card | G13: Remy Monet | H13: 202 | I13: #VALUE! | J13: #VALUE! | K13: 2009.9
A14: 10462 | B14: 44874 | C14: Fries | D14: 3.49 | E14: In-store | F14: Credit Card | G14: Remy Monet | H14: 574 | I14: #VALUE! | J14: #VALUE! | K14: 2003.26
A15: 10463 | B15: 44874 | C15: Beverages | D15: 2.95 | E15: In-store | F15: Credit Card | G15: Remy Monet | H15: 678 | I15: #VALUE! | J15: #VALUE! | K15: 2000.1
... A265: 10713 | B265: 44924 | C265: Beverages | D265: 2.95 | E265: Drive-thru | F265: Gift Card | G265: Walter Muller | H265: 678 | I265: #VALUE! | J265: #VALUE! | K265: 2000.1

Sheet Analysis
B2: Data Analysis Questions
H3: Best Selling Product PivotTable | K3: Total Revenue | M3: Revenue by Payment Method
B4: 1) What is our best selling product? | H4: Product | I4: Sum of Quantity | K4: Sum of Revenue | M4: Payment Method | N4: Sum of Revenue
B5: Beverages | H5: Beverages | I5: 37090 | K5: 821544.37 | M5: Credit Card | N5: 0.50298207
B6: 2) What is our total revenue? | H6: Fries | I6: 33272 | M6: Cash | N6: 0.291517
B7: 821544.37 | H7: Burgers | I7: 29572 | M7: Gift Card | N7: 0.20550093
B8: 3) What is the revenue breakdown by payment method? | H8: Chicken Sandwiches | I8: 11184 | M8: Grand Total | N8: 1
B9: Credit Card | H9: Sides & Other | I9: 10251
H10: Grand Total | I10: 121369
H13: These PivotTable examples are to show how to solve each question using the information created and cleaned in the breakdown sheet

Sheet Manager Revenue
A3: Row Labels | B3: Sum of Revenue
A4: Remy Monet | B4: 81931.16
A5: Walter Muller | B5: 100698.95
A6: Pablo Perez | B6: 143836.02
A7: Tom Jackson | B7: 211522.88
A8: Joao Silva | B8: 283555.36
A9: Grand Total | B9: 821544.37

Sheet Most Profit from Product
A3: Row Labels | B3: Sum of Revenue
A4: Burgers | B4: 123561.93
A5: Beverages | B5: 56129.56
A6: Fries | B6: 47716.88
A7: Chicken Sandwiches | B7: 36792.7
A8: Sides & Other | B8: 19354.29
A9: Grand Total | B9: 283555.36

Sheet Sales by Week-Month
A3: Row Labels | B3: Sum of Revenue
A4: Nov | B4: 98708.14
A5: 07-Nov | B5: 1002.99
A6: 13-Nov | B6: 45926.19
A7: 14-Nov | B7: 31543.91
A8: 19-Nov | B8: 7414.11
A9: 20-Nov | B9: 8219.12
A10: 23-Nov | B10: 4601.82
A11: Dec | B11: 184847.22
A12: 12-Dec | B12: 3003.09
A13: 13-Dec | B13: 14619.48
A14: 14-Dec | B14: 14623.63
A15: 15-Dec | B15: 14415.79
... A25: Grand Total | B25: 283555.36

Sheet Sales By Payment Method
A3: Row Labels | B3: Sum of Revenue2 | C3: Sum of Revenue
A4: Gift Card | B4: 1 | C4: 0.24088467
A5: Credit Card | B5: 1 | C5: 0.2887659
A6: Cash | B6: 1 | C6: 0.47034942
A7: Grand Total | B7: 1 | C7: 1

Sheet Detail2
A1: Details for Sum of Revenue2 - Payment Method: Gift Card
A3: Order ID | B3: Date | C3: Product | D3: Price | E3: Purchase Type | F3: Payment Method | G3: Manager | H3: Quantity | I3: City | J3: Country/region | K3: Revenue
A4: 10452 | B4: 44872 | C4: Fries | D4: 3.49 | E4: Online | F4: Gift Card | G4: Tom Jackson | H4: 574 | I4: #VALUE! | J4: #VALUE! | K4: 2003.26
A5: 10453 | B5: 44872 | C5: Beverages | D5: 2.95 | E5: Online | F5: Gift Card | G5: Pablo Perez | H5: 746 | I5: #VALUE! | J5: #VALUE! | K5: 2200.7
A6: 10454 | B6: 44872 | C6: Sides & Other | D6: 4.99 | E6: In-store | F6: Gift Card | G6: Joao Silva | H6: 201 | I6: #VALUE! | J6: #VALUE! | K6: 1002.99
A7: 10713 | B7: 44924 | C7: Beverages | D7: 2.95 | E7: Drive-thru | F7: Gift Card | G7: Walter Muller | H7: 678 | I7: #VALUE! | J7: #VALUE! | K7: 2000.1
A8: 10712 | B8: 44924 | C8: Fries | D8: 3.49 | E8: Drive-thru | F8: Gift Card | G8: Walter Muller | H8: 631 | I8: #VALUE! | J8: #VALUE! | K8: 2202.19
A9: 10711 | B9: 44924 | C9: Chicken Sandwiches | D9: 9.95 | E9: Drive-thru | F9: Gift Card | G9: Walter Muller | H9: 282 | I9: #VALUE! | J9: #VALUE! | K9: 2805.9
A10: 10710 | B10: 44924 | C10: Burgers | D10: 12.99 | E10: Drive-thru | F10: Gift Card | G10: Walter Muller | H10: 755 | I10: #VALUE! | J10: #VALUE! | K10: 9807.45
A11: 10709 | B11: 44923 | C11: Sides & Other | D11: 4.99 | E11: Drive-thru | F11: Gift Card | G11: Walter Muller | H11: 201 | I11: #VALUE! | J11: #VALUE! | K11: 1002.99
A12: 10708 | B12: 44923 | C12: Beverages | D12: 2.95 | E12: Drive-thru | F12: Gift Card | G12: Walter Muller | H12: 678 | I12: #VALUE! | J12: #VALUE! | K12: 2000.1
A13: 10707 | B13: 44923 | C13: Fries | D13: 3.49 | E13: Drive-thru | F13: Gift Card | G13: Walter Muller | H13: 631 | I13: #VALUE! | J13: #VALUE! | K13: 2202.19
A14: 10706 | B14: 44923 | C14: Chicken Sandwiches | D14: 9.95 | E14: Drive-thru | F14: Gift Card | G14: Walter Muller | H14: 302 | I14: #VALUE! | J14: #VALUE! | K14: 3004.9
A15: 10705 | B15: 44923 | C15: Burgers | D15: 12.99 | E15: Drive-thru | F15: Gift Card | G15: Walter Muller | H15: 724 | I15: #VALUE! | J15: #VALUE! | K15: 9404.76
... A61: 10608 | B61: 44903 | C61: Beverages | D61: 2.95 | E61: Online | F61: Gift Card | G61: Tom Jackson | H61: 678 | I61: #VALUE! | J61: #VALUE! | K61: 2000.1

Sheet Cards
A3: Sum of Revenue | C3: Count of Order ID | F3: Average of Revenue | I3: Row Labels | J3: Sum of Revenue
A4: 283555.36 | C4: 78 | F4: 3635.3251 | I4: 13-Nov | J4: 45926.19
I5: Grand Total | J5: 45926.19

Sheet Dashboard

Sheet Findings
B2: Select Manager -> | C2: Pablo Perez | J2: Tom Jackson
J3: Pablo Perez
B4: Geography | J4: Joao Silva
B5: Country | C5: =_xlfn.XLOOKUP(C2,Table1[Manager],Table1[Country]) -> #VALUE! | J5: Walter Muller
B6: City | C6: =_xlfn.XLOOKUP(C2,Table1[Manager],Table1[City]) -> #VALUE! | J6: Remy Monet
B8: Revenue
B9: Fries | C9: =SUMIFS(Table1[Revenue],Table1[Product],Findings!B9,Table1[Manager],Findings!$C$2) -> 17219.66
B10: Beverages | C10: =SUMIFS(Table1[Revenue],Table1[Product],Findings!B10,Table1[Manager],Findings!$C$2) -> 18402.1
B11: Sides & Other | C11: =SUMIFS(Table1[Revenue],Table1[Product],Findings!B11,Table1[Manager],Findings!$C$2) -> 9026.91
B12: Burgers | C12: =SUMIFS(Table1[Revenue],Table1[Product],Findings!B12,Table1[Manager],Findings!$C$2) -> 73692.27
B13: Chicken Sandwiches | C13: =SUMIFS(Table1[Revenue],Table1[Product],Findings!B13,Table1[Manager],Findings!$C$2) -> 18089.1
B14: Total | C14: =SUM(C9:C13) -> 136430.04
